tests/__init__.py
tests/context.py
tests/test_api_version.py
tests/test_balance.py
tests/test_ewallet.py
tests/test_qrcodes.py
tests/test_virtual_accounts.py
tests/test_xenditclient.py
xenditclient/__init__.py
xenditclient/balance.py
xenditclient/client.py
xenditclient/ewallets.py
xenditclient/exceptions.py
xenditclient/qrcodes.py
xenditclient/virtual_accounts.py
xenditclient-0.0.5.dist-info/LICENSE
xenditclient-0.0.5.dist-info/METADATA
xenditclient-0.0.5.dist-info/WHEEL
xenditclient-0.0.5.dist-info/top_level.txt
xenditclient-0.0.5.dist-info/RECORD
