Metadata-Version: 2.1
Name: xenditclient
Version: 0.0.5
Summary: Xendit REST API Client for Python
Home-page: https://github.com/dwisulfahnur/python-xendit-client
Author: Dwi Sulfahnur
Author-email: dwisulfahnur@gmail.com
License: BSD 3-Clause
Platform: UNKNOWN
Classifier: Programming Language :: Python :: 3.6
Classifier: Programming Language :: Python :: 3.7
Classifier: Programming Language :: Python :: 3.8
Classifier: Topic :: Software Development :: Libraries :: Python Modules
Requires-Python: >=3.6
Requires-Dist: requests (>=2.3.0)
